{"c56jUITXoYdSKErh56ZMzA==":"artboard%201%20copy%203-96x97.png","vUeIbrN/bxHByVSFTC4FFw==":"group%20114-1920x1280.png","ieGGBGNf/QJMWv2EjzSevA==":"8209951690075454235-2000x2667.jpg","cdSVnNfhI37fFLh08W2p8w==":"8209951690075454235-600x800.jpg","jbHQzweqnJprg/BAUhqzNg==":"xruios-600x274.png","9YiZfGuJSycEu83lLsMNSQ==":"nier_automata_house,_all_white,_copied_city,_%20(1)-512x512.jpg","C/+4u2JwMd5rWJ1KLdL+Dg==":"group%2073-600x620.png","Qxk+7wjIdxL014Ck+0El5g==":"image_2023-08-13_060818808_cleanup-600x404.png","o7uqyNanN77eqvqtb/hrcA==":"bqpssspuvshb1-1160x653.png","dE8F+XXzBVNg9DY7JiVl1g==":"moshed-2023-7-7-13-36-17-432x576.jpg","PXVaXnl1pTDVbrN8BYA2Dw==":"background3.jpg","aVlrBb5iQ15+LLwquClSSQ==":"pose-50-2079x2079.jpeg","n1dx+NZv3qks526xC0hZ5Q==":"background13.jpg","lWRRKAlyt1CBHKHR/jGy1w==":"img-20230723-wa0001-1-454x605.jpeg","sed2v6ecp94H+fg3zH3H/Q==":"screenshot%202023-07-05%20143802-939x572.png","EvEdhDziqYcaCeEGr7ECxg==":"imageedit_23-6047633745-956x501.png","+fUTf/IUWm40GxbQBUFAjg==":"xruios-1-600x274.png","qQ/3R8QDCA1ltAt+2le8+g==":"image%20(7)-1057x587.png","8VDgtlCTZIGgCj9odSKNCA==":"image%20(20)-1175x792.png","Br3Z/g3M2XntcKou9i89fA==":"imageedit_16-9341820076-946x551.png","5zZ29m6U2iFXdWinyNaRew==":"image_2023-08-13_060818808_cleanup-720x485.png","MKfdAdUqtv4MLHiG/sufZQ==":"screenshot%202023-06-25%20191950-818x583.png","JNHPLCK08JprPxfMmMy5yQ==":"screenshot%202023-07-26%20125347-843x380.png","3gxKjo+4EuDBcwvIAScdoA==":"screenshot%202023-06-27%20115020-487x522.png","E9/b06KBkHyKLdTawCrvkQ==":"screenshot%202023-07-04%20074323-898x440.png","5531GyEgv8eTFDNJ+WDP5w==":"screenshot%202023-07-04%20074433-831x543.png","8Pl+SpXKve4fJuZFZ8yp9g==":"screenshot%202023-07-05%20141414-792x441.png","Dr1sX/tV/rlVE709CTwObA==":"screenshot%202023-08-04%20102713-1402x940.png","MW9wAIHwYttwVya+FxCxNg==":"screenshot%202023-08-08%20115108-1320x943.png","xdgyYjI09+/GUtp85jgQjQ==":"screenshot%202023-08-12%20173919-593x606.png","Kgv63FTAC9Jx0KS4NCUGIg==":"screenshot%202023-08-13%20120759-1824x832.png","iNEIevAxt4FzudrdF6T1bQ==":"screenshot%202023-06-20%20130517-560x481.png","Ie07AJWYNVam3A6FE/HRpA==":"screenshot%202023-06-26%20122520-691x440.png","2jfqkGJQFBO6kFtTvfROYQ==":"screenshot%202023-06-27%20084420-675x502.png","vJCY+j9dL1Jzxq5s+xLxPw==":"screenshot%202023-06-27%20141355-428x516.png","XoZI/7mn2KJ1VtiMjQ/Ryg==":"screenshot%202023-06-29%20192023-633x502.png","NA/9xmMQuuFlChrr3I02xw==":"screenshot%202023-07-04%20074606-671x420.png","fvg8nG66fsxstT4mVbEntQ==":"screenshot%202023-07-05%20135329-639x485.png","V+8eH9EWB1dKLiXE5Cli3w==":"screenshot%202023-07-05%20144709-1245x409.png","dBVQDgTiXcLNv6Nnop0bmA==":"screenshot%202023-08-04%20072556-745x515.png","WYTPM+rBKGH9+sGVyOqIVg==":"screenshot%202023-08-04%20214231-513x429.png","t3N1+K2hocJOXFZ2xyLnvA==":"screenshot%202023-06-04%20182807-600x309.png","eSbFU9imb98gD275d51HSQ==":"screenshot%202023-06-12%20190239-600x342.png","4567hTZZR19Hx32NdgLJog==":"screenshot%202023-06-26%20122520%20-%20copy-600x382.png","qeO67gZmkFL6wzg7POhNIw==":"screenshot%202023-07-05%20135329%20-%20copy-600x455.png","YgpXdMvvvQGVI+SqNPFnTA==":"screenshot%202023-07-05%20141414%20-%20copy-600x334.png","TPqaeAWNKOBgbBInikKmbA==":"screenshot%202023-08-08%20115108%20-%20copy-600x429.png","nlZclqNhygY1vYEXQounGQ==":"untitled1073-20221208121211-283x503.png","YjXUmJGy5I0JRxz8tFaZMQ==":"acilia-283x159.png","VTIhupFgr7yMiukPKf39kQ==":"acilia-107x60.png","AgRxK6ERiR6/Cd5vl7jKfw==":"acilia2-85x64.png","7rRAQbiTEEvbe3ywaQYzOA==":"acilia2-1-85x64.png","TnOv+mzLcrClybabDtr48A==":"acilia2.png","i3iYbmBwv9DeVHLUobemmg==":"acilia2-1.png","gWt15N5hbb46CQiaA2qZfQ==":"opera-gx.jpg","lkULNx0phxqx4XNP+38cSw==":"artboard-1.png","RD/g1uO2QFMTNr5VQOxHbA==":"group-51.png","FQZbabvkJGmfE6S7I9AWxQ==":"group-52.png","a4zYmtj3XGK76EqS7UvaaQ==":"8209951690075454235-1.jpg"}